LICENSE
typing_filter/__init__.py
typing_filter/typing_filter.py
typing_filter-0.1.1.dist-info/LICENSE
typing_filter-0.1.1.dist-info/METADATA
typing_filter-0.1.1.dist-info/WHEEL
typing_filter-0.1.1.dist-info/RECORD
