Metadata-Version: 2.1
Name: typing-filter
Version: 0.1.1
Summary: Simple CLI to provide choices to a user, and let them type in phrases which filters possible options.
Home-page: https://jdelgado.net/
License: GNU GENERAL PUBLIC LICENSE
Keywords: select,choice,filter,CLI,inquirer
Author: Jonathan Delgado
Author-email: jonathandelgado0327@gmail.com
Requires-Python: >=3.7
Classifier: Intended Audience :: Developers
Classifier: License :: Other/Proprietary License
Classifier: Operating System :: OS Independent
Classifier: Programming Language :: Python :: 3
Classifier: Programming Language :: Python :: 3.7
Classifier: Programming Language :: Python :: 3.8
Classifier: Programming Language :: Python :: 3.9
Classifier: Programming Language :: Python :: 3.10
Classifier: Programming Language :: Python :: 3.11
Classifier: Programming Language :: Python :: 3.7
Project-URL: Repository, https://github.com/otanan/typing_filter
